jtoolbox/__init__.py
jtoolbox/mol_preproc_v1.py
jtoolbox/v1.py
jtoolbox-0.0.4.dist-info/METADATA
jtoolbox-0.0.4.dist-info/WHEEL
jtoolbox-0.0.4.dist-info/top_level.txt
jtoolbox-0.0.4.dist-info/RECORD
